aws_cdk/lambda_layer_kubectl_v31/__init__.py
aws_cdk/lambda_layer_kubectl_v31/py.typed
aws_cdk/lambda_layer_kubectl_v31/_jsii/__init__.py
aws_cdk/lambda_layer_kubectl_v31/_jsii/lambda-layer-kubectl-v31@2.1.0.jsii.tgz
aws_cdk_lambda_layer_kubectl_v31-2.1.0.dist-info/LICENSE
aws_cdk_lambda_layer_kubectl_v31-2.1.0.dist-info/METADATA
aws_cdk_lambda_layer_kubectl_v31-2.1.0.dist-info/NOTICE
aws_cdk_lambda_layer_kubectl_v31-2.1.0.dist-info/WHEEL
aws_cdk_lambda_layer_kubectl_v31-2.1.0.dist-info/top_level.txt
aws_cdk_lambda_layer_kubectl_v31-2.1.0.dist-info/RECORD
